mikroProcesor/pamiec_data.sv
`timescale 1ns / 1ps
//////////////////////////////////////////////////////////////////////////////////
// Company: 
// Engineer: 
// 
// Create Date: 19.10.2025 13:09:05
// Design Name: 
// Module Name: pamiec_data
// Project Name: 
// Target Devices: 
// Tool Versions: 
// Description: 
// 
// Dependencies: 
// 
// Revision:
// Revision 0.01 - File Created
// Additional Comments:
// 
//////////////////////////////////////////////////////////////////////////////////


module pamiec_data #(
        parameter ADDR_WIDTH_MEM = 8, //adres
        parameter DATA_WIDTH_MEM = 8, //dane
        parameter DATA_WIDTH_STRONY = 4//strona
    )
    (
    input wire clk,
    input wire rst, // do rejestru stron

    input wire wr_mem,
    input wire [ADDR_WIDTH_MEM-1:0] adres,
    input wire [DATA_WIDTH_MEM-1:0] dane,
    output logic [DATA_WIDTH_MEM-1:0] out
    );

    //widh strony = 4 czyli 16 stron moze byc
    localparam MEM_SIZE_Fizycznie = 1 << (ADDR_WIDTH_MEM + DATA_WIDTH_STRONY);//8+4=12 12bitów adres do mem->4k

    //rejestr stron
    logic [DATA_WIDTH_STRONY-1:0] strona;  //4 bity -> 16 stron

    // 1<<ADDR_WIDTH 1 przesuniete w lewo o 8. czyli 2^8.
    logic [DATA_WIDTH_MEM-1:0] mem [0:MEM_SIZE_Fizycznie-1]; //256 komorek po 8bit.

    //Bez resetu
    always @( posedge clk) begin : always_mem //always_ff
        if(rst) strona <= '0;
        else begin
            if(wr_mem) begin
                //dekoder
                if(adres == 8'd255) begin //rejestr stron
                    strona <= dane[DATA_WIDTH_STRONY-1:0];
                end else
                    mem[{strona, adres}] <= dane;
            end
        end
    end

    assign out = (adres == 8'd255) ? {{(DATA_WIDTH_STRONY){1'b0}}, strona} : mem[{strona, adres}];  //{4'h0, strona}
 
endmodule


////////
//stare
// module pamiec_data #(
//         parameter ADDR_WIDTH_MEM = 8, //adres
//         parameter DATA_WIDTH_MEM = 8 //dane
//     )
//     (
//     input wire clk,
//     //input wire rst,

//     input wire wr_mem,
//     input wire [ADDR_WIDTH_MEM-1:0] adres,
//     input wire [DATA_WIDTH_MEM-1:0] dane,
//     output logic [DATA_WIDTH_MEM-1:0] out
//     );

//     // 1<<ADDR_WIDTH 1 przesuniete w lewo o 8. czyli 2^8.
//     logic [DATA_WIDTH_MEM-1:0] mem [0:(1<<ADDR_WIDTH_MEM)-1]; //256 komorek po 8bit.

//     //Bez resetu
//     always @( posedge clk) begin : always_mem //always_ff
//         if(wr_mem) mem[adres] <= dane;
//         //else out <= mem[adres];
//     end
//     //Jaka różnica wsumie jest?
//     assign out = mem[adres];
 
// endmodule

mikroProcesor/tb/pamiec_data_tb.sv
`timescale 1ns/1ps

module pamiec_data_tb;

    parameter ADDR_WIDTH = 8;
    parameter DATA_WIDTH = 8;
    parameter STRONY_WIDTH = 4;

    // sygnały
    logic clk;
    logic wr_mem;
    logic [7:0] adres;
    logic [7:0] dane;
    logic [7:0] out;
    logic rst;

    // instancja modułu
    pamiec_data DUT (
        .clk(clk),
        .rst(rst),
        .wr_mem(wr_mem),
        .adres(adres),
        .dane(dane),
        .out(out)
    );

    // zegar 100 MHz
    initial clk = 1;
    always #5 clk = ~clk;

//===================

     // Zadania pomocnicze - POPRAWIONE!
    task zapisz(input [ADDR_WIDTH-1:0] addr, input [DATA_WIDTH-1:0] data);
        begin
            adres = addr;
            dane = data;
            wr_mem = 1;
            @(posedge clk);  // Czekaj na zbocze
            #1; // Czekaj na stabilizację po zboczu
            $display("[%0t] ZAPIS: adres=%0d(0x%h), dane=0x%h, out=0x%h", 
                     $time, addr, addr, data, out);
            // NIE ZERUJ wr_mem od razu! Poczekaj do następnego taktu
            wr_mem = 0;
            // Pusty cykl między operacjami
            @(posedge clk);
            #1;
        end
    endtask
    
    task odczytaj(input [ADDR_WIDTH-1:0] addr);
        begin
            adres = addr;
            wr_mem = 0;
            // Czekaj cały cykl na odczyt
            @(posedge clk);
            #1;
            $display("[%0t] ODCZYT: adres=%0d(0x%h), out=0x%h", 
                     $time, addr, addr, out);
            // Pusty cykl między operacjami
            @(posedge clk);
            #1;
        end
    endtask
    
    task zmien_strone(input [STRONY_WIDTH-1:0] strona);
        begin
            zapisz({ADDR_WIDTH{1'b1}}, {4'b0, strona});
        end
    endtask
    
    task sprawdz(input [DATA_WIDTH-1:0] expected, string message = "");
        begin
            if (out !== expected) begin
                $display("[%0t] BŁĄD: Oczekiwano 0x%h, otrzymano 0x%h %s",
                         $time, expected, out, message);
                $finish;
            end else begin
                $display("[%0t] OK: 0x%h %s", $time, out, message);
            end
        end
    endtask
    
    // ===== POPRAWIONA SEKWENCJA TESTU =====
    initial begin
        
        $display("\n=== START TESTU PAMIĘCI STRONICOWANEJ ===");
        $display("Rozmiar strony: %0d bajtów", 1 << ADDR_WIDTH);
        $display("Liczba stron: %0d", 1 << STRONY_WIDTH);
        
        // Inicjalizacja
        rst = 0;
        wr_mem = 0;
        adres = 0;
        dane = 0;
        @(posedge clk);
        
        // --------------------
        // 1. RESET
        // --------------------
        $display("\n--- 1. TEST RESETU ---");
        rst = 1;
        @(posedge clk);
        @(posedge clk); // Dwa takty resetu
        rst = 0;
        @(posedge clk);
        #1;
        
        // Sprawdź czy rejestr strony wyzerowany
        odczytaj(255);
        sprawdz(8'h00, "Rejestr strony po resecie");
        
        // --------------------
        // 2. TEST ZAPISU/ODCZYTU NA STRONIE 0
        // --------------------
        $display("\n--- 2. TEST STRONY 0 (domyślna) ---");
        
        // Zapisz na różnych adresach strony 0
        zapisz(0, 8'h01);
        zapisz(100, 8'hAA);
        zapisz(200, 8'hBB);
        zapisz(254, 8'hCC);
        
        // Odczytaj te same adresy (każdy w osobnym cyklu!)
        odczytaj(0);
        sprawdz(8'h01, "Adres 0 strony 0");
        
        odczytaj(100);
        sprawdz(8'hAA, "Adres 100 strony 0");
        
        odczytaj(200);
        sprawdz(8'hBB, "Adres 200 strony 0");
        
        odczytaj(254);
        sprawdz(8'hCC, "Adres 254 strony 0");
        
        // --------------------
        // 3. TEST ZMIANY STRONY
        // --------------------
        $display("\n--- 3. TEST ZMIANY NA STRONĘ 5 ---");
        zmien_strone(5);
        
        // Sprawdź rejestr strony
        odczytaj(255);
        sprawdz(8'h05, "Rejestr strony = 5");
        
        // Zapisz na TEJ SAMEJ lokalizacji ale innej stronie
        zapisz(0, 8'h11);
        zapisz(100, 8'h55);
        zapisz(200, 8'h66);
        
        // Odczytaj ze strony 5
        odczytaj(0);
        sprawdz(8'h11, "Adres 0 strony 5");
        
        odczytaj(100);
        sprawdz(8'h55, "Adres 100 strony 5");
        
        odczytaj(200);
        sprawdz(8'h66, "Adres 200 strony 5");
        
        // --------------------
        // 4. TEST POWROTU DO STRONY 0
        // --------------------
        $display("\n--- 4. TEST POWROTU DO STRONY 0 ---");
        zmien_strone(0);
        
        odczytaj(255);
        sprawdz(8'h00, "Rejestr strony = 0");
        
        // Sprawdź czy dane na stronie 0 nadal są
        odczytaj(0);
        sprawdz(8'h01, "Adres 0 strony 0 (nadal 0x01)");
        
        odczytaj(100);
        sprawdz(8'hAA, "Adres 100 strony 0 (nadal 0xAA)");
        
        // --------------------
        // 5. TEST WRITE-THROUGH - KLUCZOWY TEST!
        // --------------------
        $display("\n--- 5. TEST WRITE-THROUGH (1-cyklowy CPU) ---");
        
        // SCENARIUSZ: CPU 1-cyklowe - zapis i odczyt w "tym samym" cyklu
        #9;
        $display("\nScenariusz A: Zapis i NATYCHMIASTOWY odczyt w tym samym cyklu");
        adres = 80;
        dane = 8'h77;
        wr_mem = 1;
        #1; // Połowa taktu - sprawdź czy out ma już nową wartość
        if (out !== 8'h77) begin
            $display("BŁĄD: Write-through nie działa! out=0x%h, oczekiwano 0x77", out);
            #50;$finish;
        end
        $display("OK: out=0x%h (write-through działa natychmiast)", out);
        
        // Zakończ zapis
        @(posedge clk);
        #1;
        wr_mem = 0;
        
        // Odczyt w następnym cyklu (powinno być to samo)
        $display("\nScenariusz B: Odczyt w następnym cyklu");
        odczytaj(80);
        sprawdz(8'h77, "Odczyt po zapisie");
        
        // --------------------
        // 6. TEST SZYBKIEGO NADPISYWANIA
        // --------------------
        $display("\n--- 6. TEST SZYBKIEGO NADPISYWANIA ---");
        
        zmien_strone(3);
        
        // Cykl 1: Pierwszy zapis
        adres = 90;
        dane = 8'h33;
        wr_mem = 1;
        @(posedge clk);
        #1;
        sprawdz(8'h33, "Cykl 1: Zapis 0x33, out=0x33");
        
        // Cykl 2: Nadpisanie (bez zerowania wr_mem między!)
        dane = 8'h44;
        @(posedge clk);
        #1;
        sprawdz(8'h44, "Cykl 2: Nadpisanie 0x44, out=0x44");
        
        // Cykl 3: Odczyt
        wr_mem = 0;
        @(posedge clk);
        #1;
        sprawdz(8'h44, "Cykl 3: Odczyt 0x44 z pamięci");
        
        // --------------------
        // 7. TEST REJESTRU STRONY
        // --------------------
        $display("\n--- 7. TEST REJESTRU STRONY ---");
        
        // Zapis rejestru strony
        adres = 255;
        dane = 8'h09; // Strona 9
        wr_mem = 1;
        @(posedge clk);
        #1;
        sprawdz(8'h09, "Zapis strony 9 - out pokazuje zapisywaną wartość");
        wr_mem = 0;
        
        // Odczyt rejestru strony
        @(posedge clk);
        #1;
        sprawdz(8'h09, "Odczyt strony 9 z rejestru");
        
        // Zapisz coś używając nowej strony
        adres = 50;
        dane = 8'h99;
        wr_mem = 1;
        @(posedge clk);
        #1;
        sprawdz(8'h99, "Zapis 0x99 na stronie 9, adres 50");
        wr_mem = 0;
        
        // --------------------
        // 8. TEST WSZYSTKICH STRON
        // --------------------
        $display("\n--- 8. TEST WSZYSTKICH 16 STRON ---");
        
        for (int strona = 0; strona < 16; strona++) begin
            // Ustaw stronę
            adres = 255;
            dane = strona;
            wr_mem = 1;
            @(posedge clk);
            #1;
            wr_mem = 0;
            
            // Zapisz unikalną wartość
            adres = 50;
            dane = 8'h10 + strona;
            wr_mem = 1;
            @(posedge clk);
            #1;
            wr_mem = 0;
            
            // Odczytaj i sprawdź
            @(posedge clk);
            #1;
            if (out !== (8'h10 + strona)) begin
                $display("BŁĄD: Strona %0d - out=0x%h, oczekiwano 0x%h", 
                        strona, out, 8'h10 + strona);
                $finish;
            end
            $display("OK: Strona %0d - 0x%h", strona, out);
            
            // Pusty cykl między stronami
            @(posedge clk);
        end
        
        // --------------------
        // 9. TEST "CZARNEJ DZIURY"
        // --------------------
        $display("\n--- 9. TEST CZARNEJ DZIURY ---");
        $display("UWAGA: Fizyczny adres 255 w RAM jest niedostępny!");
        
        // Wróć do strony 0
        adres = 255;
        dane = 0;
        wr_mem = 1;
        @(posedge clk);
        #1;
        wr_mem = 0;
        
        // Potwierdź że adres 255 zawsze zwraca rejestr strony
        odczytaj(255);
        sprawdz(8'h00, "Adres 255 = rejestr strony (0)");
        
        // Próba dostępu do fizycznego adresu 255 jest NIEMOŻLIWA
        $display("Fizyczny bajt 255: NIEDOSTĘPNY (rezerwacja na rejestr strony)");
        
        // --------------------
        // PODSUMOWANIE
        // --------------------
        $display("\n=== WSZYSTKIE TESTY ZALICZONE! ===");
        $display("Pamięć stronnicowana działa poprawnie:");
        $display("- 16 stron po 255 bajtów (4080 bajtów dostępnych)");
        $display("- 1 bajt zarezerwowany na rejestr strony (adres 255)");
        $display("- Write-through działa (dane dostępne w tym samym takcie)");
        $display("- Izolacja stron poprawna");
        $display("- Idealne dla 1-cyklowego CPU!");
        
        #100;
        $finish;
    end


//===================



    // // test sekwencyjny
    // initial begin
    //     // inicjalizacja
    //     rst = 1;
    //     wr_mem = 0;
    //     adres  = 0;
    //     dane   = 0;
    //     #10;
    //     rst = 0;
    //     #10;
    //     adres = 255;
    //     dane = 0;
    //     wr_mem = 1;
    //     #10;
    //     wr_mem = 0;

    //     #10;
    //     for(int i=100;i<50;i++) begin
    //         wr_mem = 1;
    //         adres  = i;
    //         dane   = 50 + i;
    //     end 
    //     #10;
    //     wr_mem = 0;
    //     #10;
    //     wr_mem = 1;
    //     adres  = 255;
    //     dane   = 5;
    //     #10;
    //     for(int i=0;i<50;i++) begin
    //         wr_mem = 1;
    //         adres  = i;
    //         dane   = 50 + i;
    //     end 

    //     // zapis do adresu 0
    //     @(posedge clk);
    //     wr_mem = 1;
    //     adres  = 8'd0;
    //     dane   = 8'hAA;
    //     @(posedge clk);
    //     wr_mem = 0;

        

    //     // zapis do adresu 1
    //     @(posedge clk);
    //     wr_mem = 1;
    //     adres  = 8'd1;
    //     dane   = 8'h55;
    //     @(posedge clk);
    //     wr_mem = 0;

    //     // zapis do adresu 10
    //     @(posedge clk);
    //     wr_mem = 1;
    //     adres  = 8'd10;
    //     dane   = 8'hCC;
    //     @(posedge clk);
    //     wr_mem = 0;


    //     @(posedge clk);
    //     wr_mem = 1;
    //     adres  = 8'd255;
    //     dane   = 8'h01;
    //     @(posedge clk);
    //     wr_mem = 0;
        
    //     @(posedge clk);
    //     wr_mem = 1;
    //     adres  = 8'd0;
    //     dane   = 8'hAA;
    //     @(posedge clk);
    //     wr_mem = 0;

    //     @(posedge clk);
    //     wr_mem = 1;
    //     adres  = 8'd55;
    //     dane   = 8'hAA;
    //     @(posedge clk);
    //     wr_mem = 0;

    //     // odczyty
    //     @(posedge clk);
    //     adres = 8'd0;
    //     #1 $display("Strona 1 Adres 0 = %h", out);

    //     @(posedge clk);
    //     wr_mem = 1;
    //     adres  = 8'd255;
    //     dane   = 8'h00;
    //     @(posedge clk);
    //     wr_mem = 0;

    //    @(posedge clk);
    //     adres = 8'd0;
    //     #1 $display("Strona 0 Adres 0 = %h", out);

    //     @(posedge clk);
    //     adres = 8'd1;
    //     #1 $display("Adres 1 = %h", out);

    //     @(posedge clk);
    //     adres = 8'd10;
    //     #1 $display("Adres 10 = %h", out);

    //     @(posedge clk);
    //     adres = 8'd2;
    //     #1 $display("Adres 2 (nie zapisany) = %h", out);

    //     #300;
    //     $finish;
    // end

    // opcjonalnie do GTKWave
    initial begin
        $dumpfile("pamiec_data_tb.vcd");
        $dumpvars(0, pamiec_data_tb);
    end

endmodule

/*

        // zapis do adresu 0
        @(posedge clk);
        wr_mem = 1;
        adres  = 8'd0;
        dane   = 8'hAA;
        @(posedge clk);
        wr_mem = 0;

        // zapis do adresu 1
        @(posedge clk);
        wr_mem = 1;
        adres  = 8'd1;
        dane   = 8'h55;
        @(posedge clk);
        wr_mem = 0;

        // zapis do adresu 10
        @(posedge clk);
        wr_mem = 1;
        adres  = 8'd10;
        dane   = 8'hCC;
        @(posedge clk);
        wr_mem = 0;

        // odczyty
        @(posedge clk);
        adres = 8'd0;
        #1 $display("Adres 0 = %h", out);

        @(posedge clk);
        adres = 8'd1;
        #1 $display("Adres 1 = %h", out);

        @(posedge clk);
        adres = 8'd10;
        #1 $display("Adres 10 = %h", out);

        @(posedge clk);
        adres = 8'd2;
        #1 $display("Adres 2 (nie zapisany) = %h", out);
*/

mikroProcesor/tb/pamiec_data_tb.vcd
$date
	Thu Jan 08 21:20:33 2026
$end
$version
	Icarus Verilog
$end
$timescale
	1ps
$end
$scope module pamiec_data_tb $end
$var wire 8 ! out [7:0] $end
$var parameter 32 " ADDR_WIDTH $end
$var parameter 32 # DATA_WIDTH $end
$var parameter 32 $ STRONY_WIDTH $end
$var reg 8 % adres [7:0] $end
$var reg 1 & clk $end
$var reg 8 ' dane [7:0] $end
$var reg 1 ( rst $end
$var reg 1 ) wr_mem $end
$scope module DUT $end
$var wire 8 * adres [7:0] $end
$var wire 1 & clk $end
$var wire 8 + dane [7:0] $end
$var wire 1 ( rst $end
$var wire 1 ) wr_mem $end
$var wire 8 , out [7:0] $end
$var parameter 32 - ADDR_WIDTH_MEM $end
$var parameter 32 . DATA_WIDTH_MEM $end
$var parameter 32 / DATA_WIDTH_STRONY $end
$var parameter 44 0 MEM_SIZE_Fizycznie $end
$var reg 4 1 strona [3:0] $end
$scope begin always_mem $end
$upscope $end
$upscope $end
$scope begin $ivl_for_loop0 $end
$var integer 32 2 strona [31:0] $end
$upscope $end
$scope task odczytaj $end
$var reg 8 3 addr [7:0] $end
$upscope $end
$scope task sprawdz $end
$var reg 8 4 expected [7:0] $end
$upscope $end
$scope task zapisz $end
$var reg 8 5 addr [7:0] $end
$var reg 8 6 data [7:0] $end
$upscope $end
$scope task zmien_strone $end
$var reg 4 7 strona [3:0] $end
$upscope $end
$upscope $end
$enddefinitions $end
$comment Show the parameter values. $end
$dumpall
b1000000000000 0
b100 /
b1000 .
b1000 -
b100 $
b1000 #
b1000 "
$end
#0
$dumpvars
bx 7
bx 6
bx 5
bx 4
bx 3
b0 2
bx 1
bx ,
b0 +
b0 *
0)
0(
b0 '
1&
b0 %
bx !
$end
#5000
0&
#10000
b0 1
1(
1&
#15000
0&
#20000
1&
#25000
0&
#30000
0(
1&
#35000
0&
#40000
1&
#41000
b0 !
b0 ,
b11111111 %
b11111111 *
b11111111 3
#45000
0&
#50000
1&
#55000
0&
#60000
1&
#61000
bx !
bx ,
1)
b1 '
b1 +
b0 %
b0 *
b1 6
b0 5
b0 4
#65000
0&
#70000
b1 !
b1 ,
1&
#71000
0)
#75000
0&
#80000
1&
#81000
bx !
bx ,
1)
b10101010 '
b10101010 +
b1100100 %
b1100100 *
b10101010 6
b1100100 5
#85000
0&
#90000
b10101010 !
b10101010 ,
1&
#91000
0)
#95000
0&
#100000
1&
#101000
bx !
bx ,
1)
b10111011 '
b10111011 +
b11001000 %
b11001000 *
b10111011 6
b11001000 5
#105000
0&
#110000
b10111011 !
b10111011 ,
1&
#111000
0)
#115000
0&
#120000
1&
#121000
bx !
bx ,
1)
b11001100 '
b11001100 +
b11111110 %
b11111110 *
b11001100 6
b11111110 5
#125000
0&
#130000
b11001100 !
b11001100 ,
1&
#131000
0)
#135000
0&
#140000
1&
#141000
b1 !
b1 ,
b0 %
b0 *
b0 3
#145000
0&
#150000
1&
#155000
0&
#160000
1&
#161000
b10101010 !
b10101010 ,
b1100100 %
b1100100 *
b1100100 3
b1 4
#165000
0&
#170000
1&
#175000
0&
#180000
1&
#181000
b10111011 !
b10111011 ,
b11001000 %
b11001000 *
b11001000 3
b10101010 4
#185000
0&
#190000
1&
#195000
0&
#200000
1&
#201000
b11001100 !
b11001100 ,
b11111110 %
b11111110 *
b11111110 3
b10111011 4
#205000
0&
#210000
1&
#215000
0&
#220000
1&
#221000
b0 !
b0 ,
1)
b101 '
b101 +
b11111111 %
b11111111 *
b101 6
b11111111 5
b101 7
b11001100 4
#225000
0&
#230000
b101 !
b101 ,
b101 1
1&
#231000
0)
#235000
0&
#240000
1&
#241000
b11111111 3
#245000
0&
#250000
1&
#255000
0&
#260000
1&
#261000
bx !
bx ,
1)
b10001 '
b10001 +
b0 %
b0 *
b10001 6
b0 5
b101 4
#265000
0&
#270000
b10001 !
b10001 ,
1&
#271000
0)
#275000
0&
#280000
1&
#281000
bx !
bx ,
1)
b1010101 '
b1010101 +
b1100100 %
b1100100 *
b1010101 6
b1100100 5
#285000
0&
#290000
b1010101 !
b1010101 ,
1&
#291000
0)
#295000
0&
#300000
1&
#301000
bx !
bx ,
1)
b1100110 '
b1100110 +
b11001000 %
b11001000 *
b1100110 6
b11001000 5
#305000
0&
#310000
b1100110 !
b1100110 ,
1&
#311000
0)
#315000
0&
#320000
1&
#321000
b10001 !
b10001 ,
b0 %
b0 *
b0 3
#325000
0&
#330000
1&
#335000
0&
#340000
1&
#341000
b1010101 !
b1010101 ,
b1100100 %
b1100100 *
b1100100 3
b10001 4
#345000
0&
#350000
1&
#355000
0&
#360000
1&
#361000
b1100110 !
b1100110 ,
b11001000 %
b11001000 *
b11001000 3
b1010101 4
#365000
0&
#370000
1&
#375000
0&
#380000
1&
#381000
b101 !
b101 ,
1)
b0 '
b0 +
b11111111 %
b11111111 *
b0 6
b11111111 5
b0 7
b1100110 4
#385000
0&
#390000
b0 !
b0 ,
b0 1
1&
#391000
0)
#395000
0&
#400000
1&
#401000
b11111111 3
#405000
0&
#410000
1&
#415000
0&
#420000
1&
#421000
b1 !
b1 ,
b0 %
b0 *
b0 3
b0 4
#425000
0&
#430000
1&
#435000
0&
#440000
1&
#441000
b10101010 !
b10101010 ,
b1100100 %
b1100100 *
b1100100 3
b1 4
#445000
0&
#450000
1&
#455000
0&
#460000
1&
#461000
b10101010 4
#465000
0&
#470000
b1110111 !
b1110111 ,
1&
1)
b1110111 '
b1110111 +
b1010000 %
b1010000 *
#475000
0&
#480000
1&
#481000
b1010000 3
0)
#485000
0&
#490000
1&
#495000
0&
#500000
1&
#501000
b0 !
b0 ,
1)
b11 '
b11 +
b11111111 %
b11111111 *
b11 6
b11 7
b1110111 4
#505000
0&
#510000
b11 !
b11 ,
b11 1
1&
#511000
0)
#515000
0&
#520000
1&
#521000
bx !
bx ,
1)
b110011 '
b110011 +
b1011010 %
b1011010 *
#525000
0&
#530000
b110011 !
b110011 ,
1&
#531000
b1000100 '
b1000100 +
b110011 4
#535000
0&
#540000
b1000100 !
b1000100 ,
1&
#541000
0)
b1000100 4
#545000
0&
#550000
1&
#551000
b11 !
b11 ,
1)
b1001 '
b1001 +
b11111111 %
b11111111 *
#555000
0&
#560000
b1001 !
b1001 ,
b1001 1
1&
#561000
0)
b1001 4
#565000
0&
#570000
1&
#571000
bx !
bx ,
1)
b10011001 '
b10011001 +
b110010 %
b110010 *
#575000
0&
#580000
b10011001 !
b10011001 ,
1&
#581000
b1001 !
b1001 ,
b0 '
b0 +
b11111111 %
b11111111 *
1)
b10011001 4
#585000
0&
#590000
b0 !
b0 ,
b0 1
1&
#591000
bx !
bx ,
b10000 '
b10000 +
b110010 %
b110010 *
1)
#595000
0&
#600000
b10000 !
b10000 ,
1&
#601000
0)
#605000
0&
#610000
1&
#615000
0&
#620000
b1 1
b1 !
b1 ,
1)
b1 '
b1 +
b11111111 %
b11111111 *
b1 2
1&
#625000
0&
#630000
1&
#631000
bx !
bx ,
b10001 '
b10001 +
b110010 %
b110010 *
1)
#635000
0&
#640000
b10001 !
b10001 ,
1&
#641000
0)
#645000
0&
#650000
1&
#655000
0&
#660000
b10 1
b10 !
b10 ,
1)
b10 '
b10 +
b11111111 %
b11111111 *
b10 2
1&
#665000
0&
#670000
1&
#671000
bx !
bx ,
b10010 '
b10010 +
b110010 %
b110010 *
1)
#675000
0&
#680000
b10010 !
b10010 ,
1&
#681000
0)
#685000
0&
#690000
1&
#695000
0&
#700000
b11 1
b11 !
b11 ,
1)
b11 '
b11 +
b11111111 %
b11111111 *
b11 2
1&
#705000
0&
#710000
1&
#711000
bx !
bx ,
b10011 '
b10011 +
b110010 %
b110010 *
1)
#715000
0&
#720000
b10011 !
b10011 ,
1&
#721000
0)
#725000
0&
#730000
1&
#735000
0&
#740000
b100 1
b100 !
b100 ,
1)
b100 '
b100 +
b11111111 %
b11111111 *
b100 2
1&
#745000
0&
#750000
1&
#751000
bx !
bx ,
b10100 '
b10100 +
b110010 %
b110010 *
1)
#755000
0&
#760000
b10100 !
b10100 ,
1&
#761000
0)
#765000
0&
#770000
1&
#775000
0&
#780000
b101 1
b101 !
b101 ,
1)
b101 '
b101 +
b11111111 %
b11111111 *
b101 2
1&
#785000
0&
#790000
1&
#791000
bx !
bx ,
b10101 '
b10101 +
b110010 %
b110010 *
1)
#795000
0&
#800000
b10101 !
b10101 ,
1&
#801000
0)
#805000
0&
#810000
1&
#815000
0&
#820000
b110 1
b110 !
b110 ,
1)
b110 '
b110 +
b11111111 %
b11111111 *
b110 2
1&
#825000
0&
#830000
1&
#831000
bx !
bx ,
b10110 '
b10110 +
b110010 %
b110010 *
1)
#835000
0&
#840000
b10110 !
b10110 ,
1&
#841000
0)
#845000
0&
#850000
1&
#855000
0&
#860000
b111 1
b111 !
b111 ,
1)
b111 '
b111 +
b11111111 %
b11111111 *
b111 2
1&
#865000
0&
#870000
1&
#871000
bx !
bx ,
b10111 '
b10111 +
b110010 %
b110010 *
1)
#875000
0&
#880000
b10111 !
b10111 ,
1&
#881000
0)
#885000
0&
#890000
1&
#895000
0&
#900000
b1000 1
b1000 !
b1000 ,
1)
b1000 '
b1000 +
b11111111 %
b11111111 *
b1000 2
1&
#905000
0&
#910000
1&
#911000
bx !
bx ,
b11000 '
b11000 +
b110010 %
b110010 *
1)
#915000
0&
#920000
b11000 !
b11000 ,
1&
#921000
0)
#925000
0&
#930000
1&
#935000
0&
#940000
b1001 1
b1001 !
b1001 ,
1)
b1001 '
b1001 +
b11111111 %
b11111111 *
b1001 2
1&
#945000
0&
#950000
1&
#951000
b10011001 !
b10011001 ,
b11001 '
b11001 +
b110010 %
b110010 *
1)
#955000
0&
#960000
b11001 !
b11001 ,
1&
#961000
0)
#965000
0&
#970000
1&
#975000
0&
#980000
b1010 1
b1010 !
b1010 ,
1)
b1010 '
b1010 +
b11111111 %
b11111111 *
b1010 2
1&
#985000
0&
#990000
1&
#991000
bx !
bx ,
b11010 '
b11010 +
b110010 %
b110010 *
1)
#995000
0&
#1000000
b11010 !
b11010 ,
1&
#1001000
0)
#1005000
0&
#1010000
1&
#1015000
0&
#1020000
b1011 1
b1011 !
b1011 ,
1)
b1011 '
b1011 +
b11111111 %
b11111111 *
b1011 2
1&
#1025000
0&
#1030000
1&
#1031000
bx !
bx ,
b11011 '
b11011 +
b110010 %
b110010 *
1)
#1035000
0&
#1040000
b11011 !
b11011 ,
1&
#1041000
0)
#1045000
0&
#1050000
1&
#1055000
0&
#1060000
b1100 1
b1100 !
b1100 ,
1)
b1100 '
b1100 +
b11111111 %
b11111111 *
b1100 2
1&
#1065000
0&
#1070000
1&
#1071000
bx !
bx ,
b11100 '
b11100 +
b110010 %
b110010 *
1)
#1075000
0&
#1080000
b11100 !
b11100 ,
1&
#1081000
0)
#1085000
0&
#1090000
1&
#1095000
0&
#1100000
b1101 1
b1101 !
b1101 ,
1)
b1101 '
b1101 +
b11111111 %
b11111111 *
b1101 2
1&
#1105000
0&
#1110000
1&
#1111000
bx !
bx ,
b11101 '
b11101 +
b110010 %
b110010 *
1)
#1115000
0&
#1120000
b11101 !
b11101 ,
1&
#1121000
0)
#1125000
0&
#1130000
1&
#1135000
0&
#1140000
b1110 1
b1110 !
b1110 ,
1)
b1110 '
b1110 +
b11111111 %
b11111111 *
b1110 2
1&
#1145000
0&
#1150000
1&
#1151000
bx !
bx ,
b11110 '
b11110 +
b110010 %
b110010 *
1)
#1155000
0&
#1160000
b11110 !
b11110 ,
1&
#1161000
0)
#1165000
0&
#1170000
1&
#1175000
0&
#1180000
b1111 1
b1111 !
b1111 ,
1)
b1111 '
b1111 +
b11111111 %
b11111111 *
b1111 2
1&
#1185000
0&
#1190000
1&
#1191000
bx !
bx ,
b11111 '
b11111 +
b110010 %
b110010 *
1)
#1195000
0&
#1200000
b11111 !
b11111 ,
1&
#1201000
0)
#1205000
0&
#1210000
1&
#1215000
0&
#1220000
b1111 !
b1111 ,
1)
b0 '
b0 +
b11111111 %
b11111111 *
b10000 2
1&
#1225000
0&
#1230000
b0 !
b0 ,
b0 1
1&
#1231000
b11111111 3
0)
#1235000
0&
#1240000
1&
#1245000
0&
#1250000
1&
#1251000
b0 4
