mikroProcesor/przerwanie.sv
//////////////////////////
//Przerwanie bez masek i priorytet ma zewnetrzne przerwanie nad licznikiem

//////////////////////////

module przerwanie(
    input wire clk,
    input wire rst,

    //enable, disable .. z ID
    input wire int_enable,//sei  + RETI
    input wire int_disable,//cli

    //zrodla
    input wire ext_int,//zewnetrzne przerwanie .. przycisk
    input wire timer_int,//wewnetrzne przerwanie z licznika
    output logic [7:0] int_vector, //wektor przerwania

    output logic przerwanie
);

//rejestr
//rejestr na wejsciu od ext_int sygnalizuje ze pojawilo sie zbocze np i RETI to resetuje dopiero
logic przerwanie_en;//SREG

logic ext_int_prev;//do wykrycia zbocza
logic timer_int_prev;
logic int_a; // przerwanie przycisk
logic int_b; //przerwanie timer

//Interrupt Controller
/* To idzie najpierw do ID a potem do pc z ID idzie   */

always @(posedge clk) begin
    if(rst) begin
        przerwanie_en <= '0;
        przerwanie <= '0;
        //ext_int_en <= '0;//domyslnie nie ma przerwania
        ext_int_prev <= '0;
        timer_int_prev <= '0;
        int_a <= '0;
        int_b <= '0;
        int_vector <= '0;
    end else begin
        
        przerwanie <= '0;
        int_vector <= '0;

        if(int_enable) begin
            przerwanie_en <= 1'b1; 
        end else if(int_disable) begin
            przerwanie_en <= 1'b0; 
        end

        //zbocze i ext_int_en
        ext_int_prev <= ext_int;
        timer_int_prev <= timer_int;
        if(przerwanie_en && ext_int && ~ext_int_prev) begin
            int_a <= 1'b1;
        end
        if(przerwanie_en && timer_int && ~timer_int_prev) begin
            int_b <= 1'b1;
        end

        //priorytet
        if(int_a && przerwanie_en) begin
            przerwanie <= 1'b1;
            int_vector <= 8'h02;
            int_a <= '0;
        end else if(int_b && przerwanie_en && ~przerwanie) begin
            przerwanie <= 1'b1;
            int_vector <= 8'h04;
            int_b <= '0;
        end
    end
end

endmodule

mikroProcesor/tb/przerwanie_tb.sv
module przerwanie_tb;

logic clk;
logic rst;

logic int_enable;
logic int_disable;

logic ext_int;
logic timer_int;

logic [7:0] int_vector;

logic przerwanie;


przerwanie u_przerwanie(
    .clk(clk),
    .rst(rst),

    .int_enable(int_enable),
    .int_disable(int_disable),

    //zrodla
    .ext_int(ext_int),//zewnetrzne przerwanie .. przycisk
    .timer_int(timer_int),//wewnetrzne przerwanie z licznika

    //bez tego bo autoamtucznie jak pojawi sie przerwanie bedzie cli a RETI bedzie sei.
    //input wire ext_int_rst,//reset do przerwania z ID .. RETI


    .int_vector(int_vector), //wektor przerwania
    //On bedzie w stylu gdzies na koncu 250. a drugie przerwanie 252 254 i dokadajac wiecej pamieci prog to najstawrsze nowe bity beda jedynkami....
    .przerwanie(przerwanie)

);

initial clk = 1;
always #5 clk = ~clk;

initial begin
    $dumpfile("przerwanie_tb.vcd");
    $dumpvars(0, przerwanie_tb);
end

initial begin
    rst = 1;
    int_enable = 0;
    int_disable = 0;

    ext_int = 0;
    timer_int = 0;
    #10;
    rst = 0;
    #10;
    int_enable = 1;
    #10;
    int_enable = 0;
    #50;
    ext_int = 1;
    timer_int = 1;
    #10;
    timer_int = 0;
    int_disable = 1; //wykonywanie sie przerwaniaa
    #10
    int_disable = 0;
    #20;
    ext_int = 0;
    int_enable = 1;//wlaczenie spowrote - teraz b powinno
    #10;
    int_enable = 0;

    #50; //nowe testy
    timer_int = 1;
    #10;
    timer_int = 0;

    #500;
    $finish;

end

endmodule

mikroProcesor/tb/przerwanie_tb.vcd
$date
	Sun Jan 11 11:25:07 2026
$end
$version
	Icarus Verilog
$end
$timescale
	1s
$end
$scope module przerwanie_tb $end
$var wire 1 ! przerwanie $end
$var wire 8 " int_vector [7:0] $end
$var reg 1 # clk $end
$var reg 1 $ ext_int $end
$var reg 1 % int_disable $end
$var reg 1 & int_enable $end
$var reg 1 ' rst $end
$var reg 1 ( timer_int $end
$scope module u_przerwanie $end
$var wire 1 # clk $end
$var wire 1 $ ext_int $end
$var wire 1 % int_disable $end
$var wire 1 & int_enable $end
$var wire 1 ' rst $end
$var wire 1 ( timer_int $end
$var reg 1 ) ext_int_prev $end
$var reg 1 * int_a $end
$var reg 1 + int_b $end
$var reg 8 , int_vector [7:0] $end
$var reg 1 ! przerwanie $end
$var reg 1 - przerwanie_en $end
$var reg 1 . timer_int_prev $end
$upscope $end
$upscope $end
$enddefinitions $end
$comment Show the parameter values. $end
$dumpall
$end
#0
$dumpvars
0.
0-
b0 ,
0+
0*
0)
0(
1'
0&
0%
0$
1#
b0 "
0!
$end
#5
0#
#10
1#
0'
#15
0#
#20
1-
1#
1&
#25
0#
#30
1#
0&
#35
0#
#40
1#
#45
0#
#50
1#
#55
0#
#60
1#
#65
0#
#70
1#
#75
0#
#80
1+
1*
1.
1)
1#
1(
1$
#85
0#
#90
0*
b11111010 "
b11111010 ,
1!
0.
0-
1#
1%
0(
#95
0#
#100
b0 "
b0 ,
0!
1#
0%
#105
0#
#110
1#
#115
0#
#120
0)
1-
1#
1&
0$
#125
0#
#130
0+
b11111100 "
b11111100 ,
1!
1#
0&
#135
0#
#140
b0 "
b0 ,
0!
1#
#145
0#
#150
1#
#155
0#
#160
1#
#165
0#
#170
1#
#175
0#
#180
1+
1.
1#
1(
#185
0#
#190
0+
b11111100 "
b11111100 ,
1!
0.
1#
0(
#195
0#
#200
b0 "
b0 ,
0!
1#
